getips/__init__.py
getips/cli.py
getips-0.1.2.dist-info/entry_points.txt
getips-0.1.2.dist-info/LICENSE
getips-0.1.2.dist-info/WHEEL
getips-0.1.2.dist-info/METADATA
getips-0.1.2.dist-info/RECORD
