Metadata-Version: 2.1
Name: getips
Version: 0.1.2
Summary: Small python tool to get all IP addresses from list of domains.
Author: n4Zz2
Author-email: root@n4Zz2.com
Requires-Python: >=3.6,<4.0
Classifier: Programming Language :: Python :: 3
Classifier: Programming Language :: Python :: 3.6
Classifier: Programming Language :: Python :: 3.7
Classifier: Programming Language :: Python :: 3.8
Classifier: Programming Language :: Python :: 3.9
Requires-Dist: click (>=7.1.2,<8.0.0)
Requires-Dist: funcy (>=1.15,<2.0)
